{
  "protocol_version" : "0.0.6",
  "configuration" : {
    "version" : "(6.13.0) (explicit/7ea6b90eb94)",
    "tlc" : "__thread",
    "sigsgev" : "normal",
    "notifications" : "kqueue",
    "architecture" : "arm64",
    "disabled_features" : "com,shared_perfcounters",
    "smallconfig" : "disabled",
    "bigarrays" : "disabled",
    "softdebug" : "enabled",
    "interpreter" : "enabled",
    "llvm_support" : "disabled",
    "suspend" : "preemptive"
  },
  "memory" : {
    "Resident Size" : "188334080",
    "Virtual Size" : "420890607616",
    "minor_gc_time" : "0",
    "major_gc_time" : "6860",
    "minor_gc_count" : "0",
    "major_gc_count" : "1",
    "major_gc_time_concurrent" : "0"
 },
  "threads" : [
 {
    "is_managed" : true,
    "offset_free_hash" : "0x220db8f0c8",
    "offset_rich_hash" : "0x220db8f4ac",
    "crashed" : false,
    "native_thread_id" : "0x29e413000",
    "thread_info_addr" : "0x127b18000",
    "thread_name" : "Thread Pool Worker",
    "ctx" : {
      "IP" : "0x1afdd8290",
      "SP" : "0x29e411cc0",
      "BP" : "0x29e411d50"
  },
    "managed_frames" : [
  {
      "is_managed" : "false",
      "native_address" : "unregistered"
   }
,
  {
      "is_managed" : "true",
      "guid" : "E38A6D3E-E47C-43EB-9B2E-49C63FC0AA48",
      "token" : "0x00000",
      "native_offset" : "0x0",
      "filename" : "mscorlib.dll",
      "sizeofimage" : "0x470000",
      "timestamp" : "0xaf0ada7a",
      "il_offset" : "0xffffffff"
   }
,
  {
      "is_managed" : "true",
      "guid" : "E38A6D3E-E47C-43EB-9B2E-49C63FC0AA48",
      "token" : "0x6001fa4",
      "native_offset" : "0x0",
      "filename" : "mscorlib.dll",
      "sizeofimage" : "0x470000",
      "timestamp" : "0xaf0ada7a",
      "il_offset" : "0x00019"
   }
,
  {
      "is_managed" : "true",
      "guid" : "F3F41A8C-7505-4641-B318-00193DBBE389",
      "token" : "0x6008e6d",
      "native_offset" : "0x0",
      "filename" : "UnityEditor.CoreModule.dll",
      "sizeofimage" : "0x814000",
      "timestamp" : "0x98e4bedd",
      "il_offset" : "0x0001d"
   }
,
  {
      "is_managed" : "true",
      "guid" : "101C6C5D-5E96-4A0B-A40C-BABF450F5162",
      "token" : "0x60001df",
      "native_offset" : "0x0",
      "filename" : "UnityEditor.Android.Extensions.dll",
      "sizeofimage" : "0x52000",
      "timestamp" : "0xe96f38ee",
      "il_offset" : "0x00010"
   }
,
  {
      "is_managed" : "true",
      "guid" : "101C6C5D-5E96-4A0B-A40C-BABF450F5162",
      "token" : "0x60001db",
      "native_offset" : "0x0",
      "filename" : "UnityEditor.Android.Extensions.dll",
      "sizeofimage" : "0x52000",
      "timestamp" : "0xe96f38ee",
      "il_offset" : "0x0002d"
   }
,
  {
      "is_managed" : "true",
      "guid" : "101C6C5D-5E96-4A0B-A40C-BABF450F5162",
      "token" : "0x60001d8",
      "native_offset" : "0x0",
      "filename" : "UnityEditor.Android.Extensions.dll",
      "sizeofimage" : "0x52000",
      "timestamp" : "0xe96f38ee",
      "il_offset" : "0x0000a"
   }
,
  {
      "is_managed" : "true",
      "guid" : "101C6C5D-5E96-4A0B-A40C-BABF450F5162",
      "token" : "0x6000135",
      "native_offset" : "0x0",
      "filename" : "UnityEditor.Android.Extensions.dll",
      "sizeofimage" : "0x52000",
      "timestamp" : "0xe96f38ee",
      "il_offset" : "0x0001e"
   }
,
  {
      "is_managed" : "true",
      "guid" : "101C6C5D-5E96-4A0B-A40C-BABF450F5162",
      "token" : "0x6000134",
      "native_offset" : "0x0",
      "filename" : "UnityEditor.Android.Extensions.dll",
      "sizeofimage" : "0x52000",
      "timestamp" : "0xe96f38ee",
      "il_offset" : "0x00013"
   }
,
  {
      "is_managed" : "true",
      "guid" : "101C6C5D-5E96-4A0B-A40C-BABF450F5162",
      "token" : "0x6000248",
      "native_offset" : "0x0",
      "filename" : "UnityEditor.Android.Extensions.dll",
      "sizeofimage" : "0x52000",
      "timestamp" : "0xe96f38ee",
      "il_offset" : "0x0013b"
   }
,
  {
      "is_managed" : "true",
      "guid" : "101C6C5D-5E96-4A0B-A40C-BABF450F5162",
      "token" : "0x6000126",
      "native_offset" : "0x0",
      "filename" : "UnityEditor.Android.Extensions.dll",
      "sizeofimage" : "0x52000",
      "timestamp" : "0xe96f38ee",
      "il_offset" : "0x00039"
   }
,
  {
      "is_managed" : "true",
      "guid" : "101C6C5D-5E96-4A0B-A40C-BABF450F5162",
      "token" : "0x6000369",
      "native_offset" : "0x0",
      "filename" : "UnityEditor.Android.Extensions.dll",
      "sizeofimage" : "0x52000",
      "timestamp" : "0xe96f38ee",
      "il_offset" : "0x00027"
   }
,
  {
      "is_managed" : "true",
      "guid" : "E38A6D3E-E47C-43EB-9B2E-49C63FC0AA48",
      "token" : "0x60023fe",
      "native_offset" : "0x0",
      "filename" : "mscorlib.dll",
      "sizeofimage" : "0x470000",
      "timestamp" : "0xaf0ada7a",
      "il_offset" : "0x0000f"
   }
,
  {
      "is_managed" : "true",
      "guid" : "E38A6D3E-E47C-43EB-9B2E-49C63FC0AA48",
      "token" : "0x60023fa",
      "native_offset" : "0x0",
      "filename" : "mscorlib.dll",
      "sizeofimage" : "0x470000",
      "timestamp" : "0xaf0ada7a",
      "il_offset" : "0x00000"
   }
,
  {
      "is_managed" : "true",
      "guid" : "E38A6D3E-E47C-43EB-9B2E-49C63FC0AA48",
      "token" : "0x60023fd",
      "native_offset" : "0x0",
      "filename" : "mscorlib.dll",
      "sizeofimage" : "0x470000",
      "timestamp" : "0xaf0ada7a",
      "il_offset" : "0x00000"
   }
,
  {
      "is_managed" : "true",
      "guid" : "E38A6D3E-E47C-43EB-9B2E-49C63FC0AA48",
      "token" : "0x6001f25",
      "native_offset" : "0x0",
      "filename" : "mscorlib.dll",
      "sizeofimage" : "0x470000",
      "timestamp" : "0xaf0ada7a",
      "il_offset" : "0x00071"
   }
,
  {
      "is_managed" : "true",
      "guid" : "E38A6D3E-E47C-43EB-9B2E-49C63FC0AA48",
      "token" : "0x6001f23",
      "native_offset" : "0x0",
      "filename" : "mscorlib.dll",
      "sizeofimage" : "0x470000",
      "timestamp" : "0xaf0ada7a",
      "il_offset" : "0x00000"
   }
,
  {
      "is_managed" : "true",
      "guid" : "E38A6D3E-E47C-43EB-9B2E-49C63FC0AA48",
      "token" : "0x6002466",
      "native_offset" : "0x0",
      "filename" : "mscorlib.dll",
      "sizeofimage" : "0x470000",
      "timestamp" : "0xaf0ada7a",
      "il_offset" : "0x00034"
   }
,
  {
      "is_managed" : "true",
      "guid" : "E38A6D3E-E47C-43EB-9B2E-49C63FC0AA48",
      "token" : "0x60023fc",
      "native_offset" : "0x0",
      "filename" : "mscorlib.dll",
      "sizeofimage" : "0x470000",
      "timestamp" : "0xaf0ada7a",
      "il_offset" : "0x0004a"
   }
,
  {
      "is_managed" : "true",
      "guid" : "E38A6D3E-E47C-43EB-9B2E-49C63FC0AA48",
      "token" : "0x60023fb",
      "native_offset" : "0x0",
      "filename" : "mscorlib.dll",
      "sizeofimage" : "0x470000",
      "timestamp" : "0xaf0ada7a",
      "il_offset" : "0x00000"
   }
,
  {
      "is_managed" : "true",
      "guid" : "E38A6D3E-E47C-43EB-9B2E-49C63FC0AA48",
      "token" : "0x6002031",
      "native_offset" : "0x0",
      "filename" : "mscorlib.dll",
      "sizeofimage" : "0x470000",
      "timestamp" : "0xaf0ada7a",
      "il_offset" : "0x00074"
   }
,
  {
      "is_managed" : "true",
      "guid" : "E38A6D3E-E47C-43EB-9B2E-49C63FC0AA48",
      "token" : "0x6002046",
      "native_offset" : "0x0",
      "filename" : "mscorlib.dll",
      "sizeofimage" : "0x470000",
      "timestamp" : "0xaf0ada7a",
      "il_offset" : "0x00000"
   }
,
  {
      "is_managed" : "true",
      "guid" : "E38A6D3E-E47C-43EB-9B2E-49C63FC0AA48",
      "token" : "0x00000",
      "native_offset" : "0x0",
      "filename" : "mscorlib.dll",
      "sizeofimage" : "0x470000",
      "timestamp" : "0xaf0ada7a",
      "il_offset" : "0x0002a"
   }

  ],
  "unmanaged_frames" : [
 {
    "is_managed" : "false",
    "native_address" : "0x29a989ec0",
    "native_offset" : "0x00000"
  }
,
 {
    "is_managed" : "false",
    "native_address" : "0x29aac08cc",
    "native_offset" : "0x00000"
  }
,
 {
    "is_managed" : "false",
    "native_address" : "0x29aac0c28",
    "native_offset" : "0x00000"
  }
,
 {
    "is_managed" : "false",
    "native_address" : "0x29aac09f0",
    "native_offset" : "0x00000"
  }
,
 {
    "is_managed" : "false",
    "native_address" : "0x29a9cadc8",
    "native_offset" : "0x00000"
  }
,
 {
    "is_managed" : "false",
    "native_address" : "0x1afe294c4",
    "native_offset" : "0x00000"
  }
,
 {
    "is_managed" : "false",
    "native_address" : "0x1afe12868",
    "native_offset" : "0x00000"
  }
,
 {
    "is_managed" : "false",
    "native_address" : "0x29ab0feac",
    "native_offset" : "0x00000"
  }
,
 {
    "is_managed" : "false",
    "native_address" : "0x29ab19b88",
    "native_offset" : "0x00000"
  }
,
 {
    "is_managed" : "false",
    "native_address" : "0x29aababac",
    "native_offset" : "0x00000"
  }
,
 {
    "is_managed" : "false",
    "native_address" : "0x29aa65c18",
    "native_offset" : "0x00000"
  }
,
 {
    "is_managed" : "true",
    "guid" : "E38A6D3E-E47C-43EB-9B2E-49C63FC0AA48",
    "token" : "0x00000",
    "native_offset" : "0x0",
    "filename" : "mscorlib.dll",
    "sizeofimage" : "0x470000",
    "timestamp" : "0xaf0ada7a",
    "il_offset" : "0x00000"
  }
,
 {
    "is_managed" : "true",
    "guid" : "E38A6D3E-E47C-43EB-9B2E-49C63FC0AA48",
    "token" : "0x6001fa4",
    "native_offset" : "0x0",
    "filename" : "mscorlib.dll",
    "sizeofimage" : "0x470000",
    "timestamp" : "0xaf0ada7a",
    "il_offset" : "0x00000"
  }
,
 {
    "is_managed" : "true",
    "guid" : "F3F41A8C-7505-4641-B318-00193DBBE389",
    "token" : "0x6008e6d",
    "native_offset" : "0x0",
    "filename" : "UnityEditor.CoreModule.dll",
    "sizeofimage" : "0x814000",
    "timestamp" : "0x98e4bedd",
    "il_offset" : "0x00000"
  }
,
 {
    "is_managed" : "true",
    "guid" : "101C6C5D-5E96-4A0B-A40C-BABF450F5162",
    "token" : "0x60001df",
    "native_offset" : "0x0",
    "filename" : "UnityEditor.Android.Extensions.dll",
    "sizeofimage" : "0x52000",
    "timestamp" : "0xe96f38ee",
    "il_offset" : "0x00000"
  }
,
 {
    "is_managed" : "true",
    "guid" : "101C6C5D-5E96-4A0B-A40C-BABF450F5162",
    "token" : "0x60001db",
    "native_offset" : "0x0",
    "filename" : "UnityEditor.Android.Extensions.dll",
    "sizeofimage" : "0x52000",
    "timestamp" : "0xe96f38ee",
    "il_offset" : "0x00000"
  }
,
 {
    "is_managed" : "true",
    "guid" : "101C6C5D-5E96-4A0B-A40C-BABF450F5162",
    "token" : "0x60001d8",
    "native_offset" : "0x0",
    "filename" : "UnityEditor.Android.Extensions.dll",
    "sizeofimage" : "0x52000",
    "timestamp" : "0xe96f38ee",
    "il_offset" : "0x00000"
  }
,
 {
    "is_managed" : "true",
    "guid" : "101C6C5D-5E96-4A0B-A40C-BABF450F5162",
    "token" : "0x6000135",
    "native_offset" : "0x0",
    "filename" : "UnityEditor.Android.Extensions.dll",
    "sizeofimage" : "0x52000",
    "timestamp" : "0xe96f38ee",
    "il_offset" : "0x00000"
  }
,
 {
    "is_managed" : "true",
    "guid" : "101C6C5D-5E96-4A0B-A40C-BABF450F5162",
    "token" : "0x6000134",
    "native_offset" : "0x0",
    "filename" : "UnityEditor.Android.Extensions.dll",
    "sizeofimage" : "0x52000",
    "timestamp" : "0xe96f38ee",
    "il_offset" : "0x00000"
  }
,
 {
    "is_managed" : "true",
    "guid" : "101C6C5D-5E96-4A0B-A40C-BABF450F5162",
    "token" : "0x6000248",
    "native_offset" : "0x0",
    "filename" : "UnityEditor.Android.Extensions.dll",
    "sizeofimage" : "0x52000",
    "timestamp" : "0xe96f38ee",
    "il_offset" : "0x00000"
  }
,
 {
    "is_managed" : "true",
    "guid" : "101C6C5D-5E96-4A0B-A40C-BABF450F5162",
    "token" : "0x6000126",
    "native_offset" : "0x0",
    "filename" : "UnityEditor.Android.Extensions.dll",
    "sizeofimage" : "0x52000",
    "timestamp" : "0xe96f38ee",
    "il_offset" : "0x00000"
  }
,
 {
    "is_managed" : "true",
    "guid" : "101C6C5D-5E96-4A0B-A40C-BABF450F5162",
    "token" : "0x6000369",
    "native_offset" : "0x0",
    "filename" : "UnityEditor.Android.Extensions.dll",
    "sizeofimage" : "0x52000",
    "timestamp" : "0xe96f38ee",
    "il_offset" : "0x00000"
  }
,
 {
    "is_managed" : "true",
    "guid" : "E38A6D3E-E47C-43EB-9B2E-49C63FC0AA48",
    "token" : "0x60023fe",
    "native_offset" : "0x0",
    "filename" : "mscorlib.dll",
    "sizeofimage" : "0x470000",
    "timestamp" : "0xaf0ada7a",
    "il_offset" : "0x00000"
  }
,
 {
    "is_managed" : "true",
    "guid" : "E38A6D3E-E47C-43EB-9B2E-49C63FC0AA48",
    "token" : "0x60023fa",
    "native_offset" : "0x0",
    "filename" : "mscorlib.dll",
    "sizeofimage" : "0x470000",
    "timestamp" : "0xaf0ada7a",
    "il_offset" : "0x00000"
  }
,
 {
    "is_managed" : "true",
    "guid" : "E38A6D3E-E47C-43EB-9B2E-49C63FC0AA48",
    "token" : "0x60023fd",
    "native_offset" : "0x0",
    "filename" : "mscorlib.dll",
    "sizeofimage" : "0x470000",
    "timestamp" : "0xaf0ada7a",
    "il_offset" : "0x00000"
  }
,
 {
    "is_managed" : "true",
    "guid" : "E38A6D3E-E47C-43EB-9B2E-49C63FC0AA48",
    "token" : "0x6001f25",
    "native_offset" : "0x0",
    "filename" : "mscorlib.dll",
    "sizeofimage" : "0x470000",
    "timestamp" : "0xaf0ada7a",
    "il_offset" : "0x00000"
  }
,
 {
    "is_managed" : "true",
    "guid" : "E38A6D3E-E47C-43EB-9B2E-49C63FC0AA48",
    "token" : "0x6001f23",
    "native_offset" : "0x0",
    "filename" : "mscorlib.dll",
    "sizeofimage" : "0x470000",
    "timestamp" : "0xaf0ada7a",
    "il_offset" : "0x00000"
  }
,
 {
    "is_managed" : "true",
    "guid" : "E38A6D3E-E47C-43EB-9B2E-49C63FC0AA48",
    "token" : "0x6002466",
    "native_offset" : "0x0",
    "filename" : "mscorlib.dll",
    "sizeofimage" : "0x470000",
    "timestamp" : "0xaf0ada7a",
    "il_offset" : "0x00000"
  }
,
 {
    "is_managed" : "true",
    "guid" : "E38A6D3E-E47C-43EB-9B2E-49C63FC0AA48",
    "token" : "0x60023fc",
    "native_offset" : "0x0",
    "filename" : "mscorlib.dll",
    "sizeofimage" : "0x470000",
    "timestamp" : "0xaf0ada7a",
    "il_offset" : "0x00000"
  }
,
 {
    "is_managed" : "true",
    "guid" : "E38A6D3E-E47C-43EB-9B2E-49C63FC0AA48",
    "token" : "0x60023fb",
    "native_offset" : "0x0",
    "filename" : "mscorlib.dll",
    "sizeofimage" : "0x470000",
    "timestamp" : "0xaf0ada7a",
    "il_offset" : "0x00000"
  }
,
 {
    "is_managed" : "true",
    "guid" : "E38A6D3E-E47C-43EB-9B2E-49C63FC0AA48",
    "token" : "0x6002031",
    "native_offset" : "0x0",
    "filename" : "mscorlib.dll",
    "sizeofimage" : "0x470000",
    "timestamp" : "0xaf0ada7a",
    "il_offset" : "0x00000"
  }
,
 {
    "is_managed" : "true",
    "guid" : "E38A6D3E-E47C-43EB-9B2E-49C63FC0AA48",
    "token" : "0x6002046",
    "native_offset" : "0x0",
    "filename" : "mscorlib.dll",
    "sizeofimage" : "0x470000",
    "timestamp" : "0xaf0ada7a",
    "il_offset" : "0x00000"
  }
,
 {
    "is_managed" : "true",
    "guid" : "E38A6D3E-E47C-43EB-9B2E-49C63FC0AA48",
    "token" : "0x00000",
    "native_offset" : "0x0",
    "filename" : "mscorlib.dll",
    "sizeofimage" : "0x470000",
    "timestamp" : "0xaf0ada7a",
    "il_offset" : "0x00000"
  }
,
 {
    "is_managed" : "false",
    "native_address" : "0x29a919b74",
    "native_offset" : "0x00000"
  }
,
 {
    "is_managed" : "false",
    "native_address" : "0x29aa9f7ec",
    "native_offset" : "0x00000"
  }
,
 {
    "is_managed" : "false",
    "native_address" : "0x29aac430c",
    "native_offset" : "0x00000"
  }
,
 {
    "is_managed" : "false",
    "native_address" : "0x29aa18c70",
    "native_offset" : "0x00000"
  }
,
 {
    "is_managed" : "false",
    "native_address" : "0x29aac1638",
    "native_offset" : "0x00000"
  }
,
 {
    "is_managed" : "false",
    "native_address" : "0x29aac14e4",
    "native_offset" : "0x00000"
  }
,
 {
    "is_managed" : "false",
    "native_address" : "0x29ab40d30",
    "native_offset" : "0x00000"
  }
,
 {
    "is_managed" : "false",
    "native_address" : "0x29ab40cb8",
    "native_offset" : "0x00000"
  }
,
 {
    "is_managed" : "false",
    "native_address" : "0x1afe1226c",
    "native_offset" : "0x00000"
  }
,
 {
    "is_managed" : "false",
    "native_address" : "0x1afe0d08c",
    "native_offset" : "0x00000"
  }

 ]
},
{
  "is_managed" : true,
  "offset_free_hash" : "0x13a5b4a374",
  "offset_rich_hash" : "0x13a5b4a681",
  "crashed" : false,
  "native_thread_id" : "0x29edd7000",
  "thread_info_addr" : "0x12808f600",
  "thread_name" : "tid_24f03",
  "ctx" : {
    "IP" : "0x1afdd5654",
    "SP" : "0x29edd6470",
    "BP" : "0x29edd64f0"
 },
  "managed_frames" : [
 {
    "is_managed" : "false",
    "native_address" : "unregistered"
  }
,
 {
    "is_managed" : "true",
    "guid" : "E38A6D3E-E47C-43EB-9B2E-49C63FC0AA48",
    "token" : "0x00000",
    "native_offset" : "0x0",
    "filename" : "mscorlib.dll",
    "sizeofimage" : "0x470000",
    "timestamp" : "0xaf0ada7a",
    "il_offset" : "0xffffffff"
  }
,
 {
    "is_managed" : "true",
    "guid" : "E38A6D3E-E47C-43EB-9B2E-49C63FC0AA48",
    "token" : "0x6005989",
    "native_offset" : "0x0",
    "filename" : "mscorlib.dll",
    "sizeofimage" : "0x470000",
    "timestamp" : "0xaf0ada7a",
    "il_offset" : "0x00010"
  }
,
 {
    "is_managed" : "true",
    "guid" : "E38A6D3E-E47C-43EB-9B2E-49C63FC0AA48",
    "token" : "0x6005947",
    "native_offset" : "0x0",
    "filename" : "mscorlib.dll",
    "sizeofimage" : "0x470000",
    "timestamp" : "0xaf0ada7a",
    "il_offset" : "0x00002"
  }
,
 {
    "is_managed" : "true",
    "guid" : "E38A6D3E-E47C-43EB-9B2E-49C63FC0AA48",
    "token" : "0x600592e",
    "native_offset" : "0x0",
    "filename" : "mscorlib.dll",
    "sizeofimage" : "0x470000",
    "timestamp" : "0xaf0ada7a",
    "il_offset" : "0x00026"
  }
,
 {
    "is_managed" : "true",
    "guid" : "E38A6D3E-E47C-43EB-9B2E-49C63FC0AA48",
    "token" : "0x600592d",
    "native_offset" : "0x0",
    "filename" : "mscorlib.dll",
    "sizeofimage" : "0x470000",
    "timestamp" : "0xaf0ada7a",
    "il_offset" : "0x000a1"
  }
,
 {
    "is_managed" : "true",
    "guid" : "E38A6D3E-E47C-43EB-9B2E-49C63FC0AA48",
    "token" : "0x60054ca",
    "native_offset" : "0x0",
    "filename" : "mscorlib.dll",
    "sizeofimage" : "0x470000",
    "timestamp" : "0xaf0ada7a",
    "il_offset" : "0x000b3"
  }
,
 {
    "is_managed" : "true",
    "guid" : "E38A6D3E-E47C-43EB-9B2E-49C63FC0AA48",
    "token" : "0x60054cc",
    "native_offset" : "0x0",
    "filename" : "mscorlib.dll",
    "sizeofimage" : "0x470000",
    "timestamp" : "0xaf0ada7a",
    "il_offset" : "0x00028"
  }
,
 {
    "is_managed" : "true",
    "guid" : "F3F41A8C-7505-4641-B318-00193DBBE389",
    "token" : "0x6008e1b",
    "native_offset" : "0x0",
    "filename" : "UnityEditor.CoreModule.dll",
    "sizeofimage" : "0x814000",
    "timestamp" : "0x98e4bedd",
    "il_offset" : "0x0003d"
  }
,
 {
    "is_managed" : "true",
    "guid" : "E38A6D3E-E47C-43EB-9B2E-49C63FC0AA48",
    "token" : "0x6001f7d",
    "native_offset" : "0x0",
    "filename" : "mscorlib.dll",
    "sizeofimage" : "0x470000",
    "timestamp" : "0xaf0ada7a",
    "il_offset" : "0x00014"
  }
,
 {
    "is_managed" : "true",
    "guid" : "E38A6D3E-E47C-43EB-9B2E-49C63FC0AA48",
    "token" : "0x6001f25",
    "native_offset" : "0x0",
    "filename" : "mscorlib.dll",
    "sizeofimage" : "0x470000",
    "timestamp" : "0xaf0ada7a",
    "il_offset" : "0x00071"
  }
,
 {
    "is_managed" : "true",
    "guid" : "E38A6D3E-E47C-43EB-9B2E-49C63FC0AA48",
    "token" : "0x6001f23",
    "native_offset" : "0x0",
    "filename" : "mscorlib.dll",
    "sizeofimage" : "0x470000",
    "timestamp" : "0xaf0ada7a",
    "il_offset" : "0x00000"
  }
,
 {
    "is_managed" : "true",
    "guid" : "E38A6D3E-E47C-43EB-9B2E-49C63FC0AA48",
    "token" : "0x6001f22",
    "native_offset" : "0x0",
    "filename" : "mscorlib.dll",
    "sizeofimage" : "0x470000",
    "timestamp" : "0xaf0ada7a",
    "il_offset" : "0x0002b"
  }
,
 {
    "is_managed" : "true",
    "guid" : "E38A6D3E-E47C-43EB-9B2E-49C63FC0AA48",
    "token" : "0x6001f7f",
    "native_offset" : "0x0",
    "filename" : "mscorlib.dll",
    "sizeofimage" : "0x470000",
    "timestamp" : "0xaf0ada7a",
    "il_offset" : "0x00008"
  }
,
 {
    "is_managed" : "true",
    "guid" : "E38A6D3E-E47C-43EB-9B2E-49C63FC0AA48",
    "token" : "0x00000",
    "native_offset" : "0x0",
    "filename" : "mscorlib.dll",
    "sizeofimage" : "0x470000",
    "timestamp" : "0xaf0ada7a",
    "il_offset" : "0x00065"
  }

 ],
"unmanaged_frames" : [
{
  "is_managed" : "false",
  "native_address" : "0x29a989ec0",
  "native_offset" : "0x00000"
 }
,
{
  "is_managed" : "false",
  "native_address" : "0x29aac08cc",
  "native_offset" : "0x00000"
 }
,
{
  "is_managed" : "false",
  "native_address" : "0x29aac0c28",
  "native_offset" : "0x00000"
 }
,
{
  "is_managed" : "false",
  "native_address" : "0x29aac09f0",
  "native_offset" : "0x00000"
 }
,
{
  "is_managed" : "false",
  "native_address" : "0x29a9cadc8",
  "native_offset" : "0x00000"
 }
,
{
  "is_managed" : "false",
  "native_address" : "0x1afe294c4",
  "native_offset" : "0x00000"
 }
,
{
  "is_managed" : "false",
  "native_address" : "0x29aa15a1c",
  "native_offset" : "0x00000"
 }
,
{
  "is_managed" : "false",
  "native_address" : "0x29aa10c80",
  "native_offset" : "0x00000"
 }
,
{
  "is_managed" : "false",
  "native_address" : "0x29aa48120",
  "native_offset" : "0x00000"
 }
,
{
  "is_managed" : "false",
  "native_address" : "0x29aa5c1e0",
  "native_offset" : "0x00000"
 }
,
{
  "is_managed" : "true",
  "guid" : "E38A6D3E-E47C-43EB-9B2E-49C63FC0AA48",
  "token" : "0x00000",
  "native_offset" : "0x0",
  "filename" : "mscorlib.dll",
  "sizeofimage" : "0x470000",
  "timestamp" : "0xaf0ada7a",
  "il_offset" : "0x00000"
 }
,
{
  "is_managed" : "true",
  "guid" : "E38A6D3E-E47C-43EB-9B2E-49C63FC0AA48",
  "token" : "0x6005989",
  "native_offset" : "0x0",
  "filename" : "mscorlib.dll",
  "sizeofimage" : "0x470000",
  "timestamp" : "0xaf0ada7a",
  "il_offset" : "0x00000"
 }
,
{
  "is_managed" : "true",
  "guid" : "E38A6D3E-E47C-43EB-9B2E-49C63FC0AA48",
  "token" : "0x6005947",
  "native_offset" : "0x0",
  "filename" : "mscorlib.dll",
  "sizeofimage" : "0x470000",
  "timestamp" : "0xaf0ada7a",
  "il_offset" : "0x00000"
 }
,
{
  "is_managed" : "true",
  "guid" : "E38A6D3E-E47C-43EB-9B2E-49C63FC0AA48",
  "token" : "0x600592e",
  "native_offset" : "0x0",
  "filename" : "mscorlib.dll",
  "sizeofimage" : "0x470000",
  "timestamp" : "0xaf0ada7a",
  "il_offset" : "0x00000"
 }
,
{
  "is_managed" : "true",
  "guid" : "E38A6D3E-E47C-43EB-9B2E-49C63FC0AA48",
  "token" : "0x600592d",
  "native_offset" : "0x0",
  "filename" : "mscorlib.dll",
  "sizeofimage" : "0x470000",
  "timestamp" : "0xaf0ada7a",
  "il_offset" : "0x00000"
 }
,
{
  "is_managed" : "true",
  "guid" : "E38A6D3E-E47C-43EB-9B2E-49C63FC0AA48",
  "token" : "0x60054ca",
  "native_offset" : "0x0",
  "filename" : "mscorlib.dll",
  "sizeofimage" : "0x470000",
  "timestamp" : "0xaf0ada7a",
  "il_offset" : "0x00000"
 }
,
{
  "is_managed" : "true",
  "guid" : "E38A6D3E-E47C-43EB-9B2E-49C63FC0AA48",
  "token" : "0x60054cc",
  "native_offset" : "0x0",
  "filename" : "mscorlib.dll",
  "sizeofimage" : "0x470000",
  "timestamp" : "0xaf0ada7a",
  "il_offset" : "0x00000"
 }
,
{
  "is_managed" : "true",
  "guid" : "F3F41A8C-7505-4641-B318-00193DBBE389",
  "token" : "0x6008e1b",
  "native_offset" : "0x0",
  "filename" : "UnityEditor.CoreModule.dll",
  "sizeofimage" : "0x814000",
  "timestamp" : "0x98e4bedd",
  "il_offset" : "0x00000"
 }
,
{
  "is_managed" : "true",
  "guid" : "E38A6D3E-E47C-43EB-9B2E-49C63FC0AA48",
  "token" : "0x6001f7d",
  "native_offset" : "0x0",
  "filename" : "mscorlib.dll",
  "sizeofimage" : "0x470000",
  "timestamp" : "0xaf0ada7a",
  "il_offset" : "0x00000"
 }
,
{
  "is_managed" : "true",
  "guid" : "E38A6D3E-E47C-43EB-9B2E-49C63FC0AA48",
  "token" : "0x6001f25",
  "native_offset" : "0x0",
  "filename" : "mscorlib.dll",
  "sizeofimage" : "0x470000",
  "timestamp" : "0xaf0ada7a",
  "il_offset" : "0x00000"
 }
,
{
  "is_managed" : "true",
  "guid" : "E38A6D3E-E47C-43EB-9B2E-49C63FC0AA48",
  "token" : "0x6001f23",
  "native_offset" : "0x0",
  "filename" : "mscorlib.dll",
  "sizeofimage" : "0x470000",
  "timestamp" : "0xaf0ada7a",
  "il_offset" : "0x00000"
 }
,
{
  "is_managed" : "true",
  "guid" : "E38A6D3E-E47C-43EB-9B2E-49C63FC0AA48",
  "token" : "0x6001f22",
  "native_offset" : "0x0",
  "filename" : "mscorlib.dll",
  "sizeofimage" : "0x470000",
  "timestamp" : "0xaf0ada7a",
  "il_offset" : "0x00000"
 }
,
{
  "is_managed" : "true",
  "guid" : "E38A6D3E-E47C-43EB-9B2E-49C63FC0AA48",
  "token" : "0x6001f7f",
  "native_offset" : "0x0",
  "filename" : "mscorlib.dll",
  "sizeofimage" : "0x470000",
  "timestamp" : "0xaf0ada7a",
  "il_offset" : "0x00000"
 }
,
{
  "is_managed" : "true",
  "guid" : "E38A6D3E-E47C-43EB-9B2E-49C63FC0AA48",
  "token" : "0x00000",
  "native_offset" : "0x0",
  "filename" : "mscorlib.dll",
  "sizeofimage" : "0x470000",
  "timestamp" : "0xaf0ada7a",
  "il_offset" : "0x00000"
 }
,
{
  "is_managed" : "false",
  "native_address" : "0x29a919b74",
  "native_offset" : "0x00000"
 }
,
{
  "is_managed" : "false",
  "native_address" : "0x29aa9f7ec",
  "native_offset" : "0x00000"
 }
,
{
  "is_managed" : "false",
  "native_address" : "0x29aaa13e8",
  "native_offset" : "0x00000"
 }
,
{
  "is_managed" : "false",
  "native_address" : "0x29aac172c",
  "native_offset" : "0x00000"
 }
,
{
  "is_managed" : "false",
  "native_address" : "0x29aac14e4",
  "native_offset" : "0x00000"
 }
,
{
  "is_managed" : "false",
  "native_address" : "0x29ab40d30",
  "native_offset" : "0x00000"
 }
,
{
  "is_managed" : "false",
  "native_address" : "0x29ab40cb8",
  "native_offset" : "0x00000"
 }
,
{
  "is_managed" : "false",
  "native_address" : "0x1afe1226c",
  "native_offset" : "0x00000"
 }
,
{
  "is_managed" : "false",
  "native_address" : "0x1afe0d08c",
  "native_offset" : "0x00000"
 }

]
},
{
"is_managed" : false,
"offset_free_hash" : "0x0",
"offset_rich_hash" : "0x0",
"crashed" : false,
"native_thread_id" : "0x29b3ff000",
"thread_info_addr" : "0x1278ce800",
"thread_name" : "Debugger agent",
"ctx" : {
  "IP" : "0x1afddcea4",
  "SP" : "0x29b3feaa0",
  "BP" : "0x29b3feae0"
},
"unmanaged_frames" : [
{
  "is_managed" : "false",
  "native_address" : "0x29a989ec0",
  "native_offset" : "0x00000"
 }
,
{
  "is_managed" : "false",
  "native_address" : "0x29aac08cc",
  "native_offset" : "0x00000"
 }
,
{
  "is_managed" : "false",
  "native_address" : "0x29aac0c28",
  "native_offset" : "0x00000"
 }
,
{
  "is_managed" : "false",
  "native_address" : "0x29aac09f0",
  "native_offset" : "0x00000"
 }
,
{
  "is_managed" : "false",
  "native_address" : "0x29a9cadc8",
  "native_offset" : "0x00000"
 }
,
{
  "is_managed" : "false",
  "native_address" : "0x1afe294c4",
  "native_offset" : "0x00000"
 }
,
{
  "is_managed" : "false",
  "native_address" : "0x29aa005d4",
  "native_offset" : "0x00000"
 }
,
{
  "is_managed" : "false",
  "native_address" : "0x29a9f7954",
  "native_offset" : "0x00000"
 }
,
{
  "is_managed" : "false",
  "native_address" : "0x29aac1638",
  "native_offset" : "0x00000"
 }
,
{
  "is_managed" : "false",
  "native_address" : "0x29aac14e4",
  "native_offset" : "0x00000"
 }
,
{
  "is_managed" : "false",
  "native_address" : "0x29ab40d30",
  "native_offset" : "0x00000"
 }
,
{
  "is_managed" : "false",
  "native_address" : "0x29ab40cb8",
  "native_offset" : "0x00000"
 }
,
{
  "is_managed" : "false",
  "native_address" : "0x1afe1226c",
  "native_offset" : "0x00000"
 }
,
{
  "is_managed" : "false",
  "native_address" : "0x1afe0d08c",
  "native_offset" : "0x00000"
 }

]
},
{
"is_managed" : false,
"offset_free_hash" : "0x0",
"offset_rich_hash" : "0x0",
"crashed" : true,
"native_thread_id" : "0x107e24580",
"thread_info_addr" : "0x1280efa00",
"thread_name" : "tid_103",
"ctx" : {
  "IP" : "0x1afe26884",
  "SP" : "0x16dbbbbb0",
  "BP" : "0x16dbbbd50"
},
"unmanaged_frames" : [
{
  "is_managed" : "false",
  "native_address" : "0x29a989ec0",
  "native_offset" : "0x00000"
 }
,
{
  "is_managed" : "false",
  "native_address" : "0x29aac08cc",
  "native_offset" : "0x00000"
 }
,
{
  "is_managed" : "false",
  "native_address" : "0x29aac0c28",
  "native_offset" : "0x00000"
 }
,
{
  "is_managed" : "false",
  "native_address" : "0x29aac1218",
  "native_offset" : "0x00000"
 }
,
{
  "is_managed" : "false",
  "native_address" : "0x29a9cbc14",
  "native_offset" : "0x00000"
 }
,
{
  "is_managed" : "false",
  "native_address" : "0x29a98df50",
  "native_offset" : "0x00000"
 }
,
{
  "is_managed" : "false",
  "native_address" : "0x29a9168b4",
  "native_offset" : "0x00000"
 }
,
{
  "is_managed" : "false",
  "native_address" : "0x1afe294c4",
  "native_offset" : "0x00000"
 }
,
{
  "is_managed" : "false",
  "native_address" : "0x1041a70c4",
  "native_offset" : "0x00000"
 }
,
{
  "is_managed" : "false",
  "native_address" : "0x1041958a0",
  "native_offset" : "0x00000"
 }
,
{
  "is_managed" : "false",
  "native_address" : "0x104195b9c",
  "native_offset" : "0x00000"
 }
,
{
  "is_managed" : "false",
  "native_address" : "0x1040c828c",
  "native_offset" : "0x00000"
 }
,
{
  "is_managed" : "false",
  "native_address" : "0x104142800",
  "native_offset" : "0x00000"
 }
,
{
  "is_managed" : "false",
  "native_address" : "0x10411f83c",
  "native_offset" : "0x00000"
 }
,
{
  "is_managed" : "false",
  "native_address" : "0x1041212f8",
  "native_offset" : "0x00000"
 }
,
{
  "is_managed" : "false",
  "native_address" : "0x103d03074",
  "native_offset" : "0x00000"
 }
,
{
  "is_managed" : "false",
  "native_address" : "0x104a8b294",
  "native_offset" : "0x00000"
 }
,
{
  "is_managed" : "false",
  "native_address" : "0x1afed2ddc",
  "native_offset" : "0x00000"
 }
,
{
  "is_managed" : "false",
  "native_address" : "0x1aff77578",
  "native_offset" : "0x00000"
 }
,
{
  "is_managed" : "false",
  "native_address" : "0x1aff774e4",
  "native_offset" : "0x00000"
 }
,
{
  "is_managed" : "false",
  "native_address" : "0x1afea1a74",
  "native_offset" : "0x00000"
 }
,
{
  "is_managed" : "false",
  "native_address" : "0x1b0d5ee48",
  "native_offset" : "0x00000"
 }
,
{
  "is_managed" : "false",
  "native_address" : "0x1b2a4493c",
  "native_offset" : "0x00000"
 }
,
{
  "is_managed" : "false",
  "native_address" : "0x1b2a44654",
  "native_offset" : "0x00000"
 }
,
{
  "is_managed" : "false",
  "native_address" : "0x1b2a42078",
  "native_offset" : "0x00000"
 }
,
{
  "is_managed" : "false",
  "native_address" : "0x1b2a41c58",
  "native_offset" : "0x00000"
 }
,
{
  "is_managed" : "false",
  "native_address" : "0x1b0d8b9e8",
  "native_offset" : "0x00000"
 }
,
{
  "is_managed" : "false",
  "native_address" : "0x1b0d8b820",
  "native_offset" : "0x00000"
 }
,
{
  "is_managed" : "false",
  "native_address" : "0x1b66698f4",
  "native_offset" : "0x00000"
 }
,
{
  "is_managed" : "false",
  "native_address" : "0x1b666924c",
  "native_offset" : "0x00000"
 }
,
{
  "is_managed" : "false",
  "native_address" : "0x1b66623f8",
  "native_offset" : "0x00000"
 }
,
{
  "is_managed" : "false",
  "native_address" : "0x1b8b0e3fc",
  "native_offset" : "0x00000"
 }
,
{
  "is_managed" : "false",
  "native_address" : "0x1b2a3bfa4",
  "native_offset" : "0x00000"
 }
,
{
  "is_managed" : "false",
  "native_address" : "0x1b2a3a4c4",
  "native_offset" : "0x00000"
 }
,
{
  "is_managed" : "false",
  "native_address" : "0x1b2a2c690",
  "native_offset" : "0x00000"
 }
,
{
  "is_managed" : "false",
  "native_address" : "0x1b29fdda8",
  "native_offset" : "0x00000"
 }
,
{
  "is_managed" : "false",
  "native_address" : "0x104a89798",
  "native_offset" : "0x00000"
 }
,
{
  "is_managed" : "false",
  "native_address" : "0x104a89ad0",
  "native_offset" : "0x00000"
 }
,
{
  "is_managed" : "false",
  "native_address" : "0x107db1088",
  "native_offset" : "0x00000"
 }

]
},
{
"is_managed" : false,
"offset_free_hash" : "0x0",
"offset_rich_hash" : "0x0",
"crashed" : false,
"native_thread_id" : "0x29e207000",
"thread_info_addr" : "0x127f66000",
"thread_name" : "tid_25403",
"ctx" : {
  "IP" : "0x1afdd8290",
  "SP" : "0x29e206c20",
  "BP" : "0x29e206cb0"
},
"unmanaged_frames" : [
{
  "is_managed" : "false",
  "native_address" : "0x29a989ec0",
  "native_offset" : "0x00000"
 }
,
{
  "is_managed" : "false",
  "native_address" : "0x29aac08cc",
  "native_offset" : "0x00000"
 }
,
{
  "is_managed" : "false",
  "native_address" : "0x29aac0c28",
  "native_offset" : "0x00000"
 }
,
{
  "is_managed" : "false",
  "native_address" : "0x29aac09f0",
  "native_offset" : "0x00000"
 }
,
{
  "is_managed" : "false",
  "native_address" : "0x29a9cadc8",
  "native_offset" : "0x00000"
 }
,
{
  "is_managed" : "false",
  "native_address" : "0x1afe294c4",
  "native_offset" : "0x00000"
 }
,
{
  "is_managed" : "false",
  "native_address" : "0x1afe12868",
  "native_offset" : "0x00000"
 }
,
{
  "is_managed" : "false",
  "native_address" : "0x29ab0feac",
  "native_offset" : "0x00000"
 }
,
{
  "is_managed" : "false",
  "native_address" : "0x29ab19b88",
  "native_offset" : "0x00000"
 }
,
{
  "is_managed" : "false",
  "native_address" : "0x29aa18654",
  "native_offset" : "0x00000"
 }
,
{
  "is_managed" : "false",
  "native_address" : "0x29aac1638",
  "native_offset" : "0x00000"
 }
,
{
  "is_managed" : "false",
  "native_address" : "0x29aac14e4",
  "native_offset" : "0x00000"
 }
,
{
  "is_managed" : "false",
  "native_address" : "0x29ab40d30",
  "native_offset" : "0x00000"
 }
,
{
  "is_managed" : "false",
  "native_address" : "0x29ab40cb8",
  "native_offset" : "0x00000"
 }
,
{
  "is_managed" : "false",
  "native_address" : "0x1afe1226c",
  "native_offset" : "0x00000"
 }
,
{
  "is_managed" : "false",
  "native_address" : "0x1afe0d08c",
  "native_offset" : "0x00000"
 }

]
},
{
"is_managed" : false,
"offset_free_hash" : "0x0",
"offset_rich_hash" : "0x0",
"crashed" : false,
"native_thread_id" : "0x29e61f000",
"thread_info_addr" : "0x128475200",
"thread_name" : "Thread Pool Worker",
"ctx" : {
  "IP" : "0x1afdd4924",
  "SP" : "0x29e61edb0",
  "BP" : "0x29e61ee50"
},
"unmanaged_frames" : [
{
  "is_managed" : "false",
  "native_address" : "0x29a989ec0",
  "native_offset" : "0x00000"
 }
,
{
  "is_managed" : "false",
  "native_address" : "0x29aac08cc",
  "native_offset" : "0x00000"
 }
,
{
  "is_managed" : "false",
  "native_address" : "0x29aac0c28",
  "native_offset" : "0x00000"
 }
,
{
  "is_managed" : "false",
  "native_address" : "0x29aac09f0",
  "native_offset" : "0x00000"
 }
,
{
  "is_managed" : "false",
  "native_address" : "0x29a9cadc8",
  "native_offset" : "0x00000"
 }
,
{
  "is_managed" : "false",
  "native_address" : "0x1afe294c4",
  "native_offset" : "0x00000"
 }
,
{
  "is_managed" : "false",
  "native_address" : "0x29aa18e4c",
  "native_offset" : "0x00000"
 }
,
{
  "is_managed" : "false",
  "native_address" : "0x29aac1638",
  "native_offset" : "0x00000"
 }
,
{
  "is_managed" : "false",
  "native_address" : "0x29aac14e4",
  "native_offset" : "0x00000"
 }
,
{
  "is_managed" : "false",
  "native_address" : "0x29ab40d30",
  "native_offset" : "0x00000"
 }
,
{
  "is_managed" : "false",
  "native_address" : "0x29ab40cb8",
  "native_offset" : "0x00000"
 }
,
{
  "is_managed" : "false",
  "native_address" : "0x1afe1226c",
  "native_offset" : "0x00000"
 }
,
{
  "is_managed" : "false",
  "native_address" : "0x1afe0d08c",
  "native_offset" : "0x00000"
 }

]
},
{
"is_managed" : true,
"offset_free_hash" : "0x13a5b4a374",
"offset_rich_hash" : "0x13a5b4a5f6",
"crashed" : false,
"native_thread_id" : "0x29ebcb000",
"thread_info_addr" : "0x117848000",
"thread_name" : "tid_25103",
"ctx" : {
  "IP" : "0x1afdd5654",
  "SP" : "0x29ebca470",
  "BP" : "0x29ebca4f0"
},
"managed_frames" : [
{
  "is_managed" : "false",
  "native_address" : "unregistered"
 }
,
{
  "is_managed" : "true",
  "guid" : "E38A6D3E-E47C-43EB-9B2E-49C63FC0AA48",
  "token" : "0x00000",
  "native_offset" : "0x0",
  "filename" : "mscorlib.dll",
  "sizeofimage" : "0x470000",
  "timestamp" : "0xaf0ada7a",
  "il_offset" : "0xffffffff"
 }
,
{
  "is_managed" : "true",
  "guid" : "E38A6D3E-E47C-43EB-9B2E-49C63FC0AA48",
  "token" : "0x6005989",
  "native_offset" : "0x0",
  "filename" : "mscorlib.dll",
  "sizeofimage" : "0x470000",
  "timestamp" : "0xaf0ada7a",
  "il_offset" : "0x00010"
 }
,
{
  "is_managed" : "true",
  "guid" : "E38A6D3E-E47C-43EB-9B2E-49C63FC0AA48",
  "token" : "0x6005947",
  "native_offset" : "0x0",
  "filename" : "mscorlib.dll",
  "sizeofimage" : "0x470000",
  "timestamp" : "0xaf0ada7a",
  "il_offset" : "0x00002"
 }
,
{
  "is_managed" : "true",
  "guid" : "E38A6D3E-E47C-43EB-9B2E-49C63FC0AA48",
  "token" : "0x600592e",
  "native_offset" : "0x0",
  "filename" : "mscorlib.dll",
  "sizeofimage" : "0x470000",
  "timestamp" : "0xaf0ada7a",
  "il_offset" : "0x00026"
 }
,
{
  "is_managed" : "true",
  "guid" : "E38A6D3E-E47C-43EB-9B2E-49C63FC0AA48",
  "token" : "0x600592d",
  "native_offset" : "0x0",
  "filename" : "mscorlib.dll",
  "sizeofimage" : "0x470000",
  "timestamp" : "0xaf0ada7a",
  "il_offset" : "0x000a1"
 }
,
{
  "is_managed" : "true",
  "guid" : "E38A6D3E-E47C-43EB-9B2E-49C63FC0AA48",
  "token" : "0x60054ca",
  "native_offset" : "0x0",
  "filename" : "mscorlib.dll",
  "sizeofimage" : "0x470000",
  "timestamp" : "0xaf0ada7a",
  "il_offset" : "0x00028"
 }
,
{
  "is_managed" : "true",
  "guid" : "E38A6D3E-E47C-43EB-9B2E-49C63FC0AA48",
  "token" : "0x60054cc",
  "native_offset" : "0x0",
  "filename" : "mscorlib.dll",
  "sizeofimage" : "0x470000",
  "timestamp" : "0xaf0ada7a",
  "il_offset" : "0x00028"
 }
,
{
  "is_managed" : "true",
  "guid" : "F3F41A8C-7505-4641-B318-00193DBBE389",
  "token" : "0x6008e1b",
  "native_offset" : "0x0",
  "filename" : "UnityEditor.CoreModule.dll",
  "sizeofimage" : "0x814000",
  "timestamp" : "0x98e4bedd",
  "il_offset" : "0x0003d"
 }
,
{
  "is_managed" : "true",
  "guid" : "E38A6D3E-E47C-43EB-9B2E-49C63FC0AA48",
  "token" : "0x6001f7d",
  "native_offset" : "0x0",
  "filename" : "mscorlib.dll",
  "sizeofimage" : "0x470000",
  "timestamp" : "0xaf0ada7a",
  "il_offset" : "0x00014"
 }
,
{
  "is_managed" : "true",
  "guid" : "E38A6D3E-E47C-43EB-9B2E-49C63FC0AA48",
  "token" : "0x6001f25",
  "native_offset" : "0x0",
  "filename" : "mscorlib.dll",
  "sizeofimage" : "0x470000",
  "timestamp" : "0xaf0ada7a",
  "il_offset" : "0x00071"
 }
,
{
  "is_managed" : "true",
  "guid" : "E38A6D3E-E47C-43EB-9B2E-49C63FC0AA48",
  "token" : "0x6001f23",
  "native_offset" : "0x0",
  "filename" : "mscorlib.dll",
  "sizeofimage" : "0x470000",
  "timestamp" : "0xaf0ada7a",
  "il_offset" : "0x00000"
 }
,
{
  "is_managed" : "true",
  "guid" : "E38A6D3E-E47C-43EB-9B2E-49C63FC0AA48",
  "token" : "0x6001f22",
  "native_offset" : "0x0",
  "filename" : "mscorlib.dll",
  "sizeofimage" : "0x470000",
  "timestamp" : "0xaf0ada7a",
  "il_offset" : "0x0002b"
 }
,
{
  "is_managed" : "true",
  "guid" : "E38A6D3E-E47C-43EB-9B2E-49C63FC0AA48",
  "token" : "0x6001f7f",
  "native_offset" : "0x0",
  "filename" : "mscorlib.dll",
  "sizeofimage" : "0x470000",
  "timestamp" : "0xaf0ada7a",
  "il_offset" : "0x00008"
 }
,
{
  "is_managed" : "true",
  "guid" : "E38A6D3E-E47C-43EB-9B2E-49C63FC0AA48",
  "token" : "0x00000",
  "native_offset" : "0x0",
  "filename" : "mscorlib.dll",
  "sizeofimage" : "0x470000",
  "timestamp" : "0xaf0ada7a",
  "il_offset" : "0x00065"
 }

],
"unmanaged_frames" : [
{
"is_managed" : "false",
"native_address" : "0x29a989ec0",
"native_offset" : "0x00000"
}
,
{
"is_managed" : "false",
"native_address" : "0x29aac08cc",
"native_offset" : "0x00000"
}
,
{
"is_managed" : "false",
"native_address" : "0x29aac0c28",
"native_offset" : "0x00000"
}
,
{
"is_managed" : "false",
"native_address" : "0x29aac09f0",
"native_offset" : "0x00000"
}
,
{
"is_managed" : "false",
"native_address" : "0x29a9cadc8",
"native_offset" : "0x00000"
}
,
{
"is_managed" : "false",
"native_address" : "0x1afe294c4",
"native_offset" : "0x00000"
}
,
{
"is_managed" : "false",
"native_address" : "0x29aa15a1c",
"native_offset" : "0x00000"
}
,
{
"is_managed" : "false",
"native_address" : "0x29aa10c80",
"native_offset" : "0x00000"
}
,
{
"is_managed" : "false",
"native_address" : "0x29aa48120",
"native_offset" : "0x00000"
}
,
{
"is_managed" : "false",
"native_address" : "0x29aa5c1e0",
"native_offset" : "0x00000"
}
,
{
"is_managed" : "true",
"guid" : "E38A6D3E-E47C-43EB-9B2E-49C63FC0AA48",
"token" : "0x00000",
"native_offset" : "0x0",
"filename" : "mscorlib.dll",
"sizeofimage" : "0x470000",
"timestamp" : "0xaf0ada7a",
"il_offset" : "0x00000"
}
,
{
"is_managed" : "true",
"guid" : "E38A6D3E-E47C-43EB-9B2E-49C63FC0AA48",
"token" : "0x6005989",
"native_offset" : "0x0",
"filename" : "mscorlib.dll",
"sizeofimage" : "0x470000",
"timestamp" : "0xaf0ada7a",
"il_offset" : "0x00000"
}
,
{
"is_managed" : "true",
"guid" : "E38A6D3E-E47C-43EB-9B2E-49C63FC0AA48",
"token" : "0x6005947",
"native_offset" : "0x0",
"filename" : "mscorlib.dll",
"sizeofimage" : "0x470000",
"timestamp" : "0xaf0ada7a",
"il_offset" : "0x00000"
}
,
{
"is_managed" : "true",
"guid" : "E38A6D3E-E47C-43EB-9B2E-49C63FC0AA48",
"token" : "0x600592e",
"native_offset" : "0x0",
"filename" : "mscorlib.dll",
"sizeofimage" : "0x470000",
"timestamp" : "0xaf0ada7a",
"il_offset" : "0x00000"
}
,
{
"is_managed" : "true",
"guid" : "E38A6D3E-E47C-43EB-9B2E-49C63FC0AA48",
"token" : "0x600592d",
"native_offset" : "0x0",
"filename" : "mscorlib.dll",
"sizeofimage" : "0x470000",
"timestamp" : "0xaf0ada7a",
"il_offset" : "0x00000"
}
,
{
"is_managed" : "true",
"guid" : "E38A6D3E-E47C-43EB-9B2E-49C63FC0AA48",
"token" : "0x60054ca",
"native_offset" : "0x0",
"filename" : "mscorlib.dll",
"sizeofimage" : "0x470000",
"timestamp" : "0xaf0ada7a",
"il_offset" : "0x00000"
}
,
{
"is_managed" : "true",
"guid" : "E38A6D3E-E47C-43EB-9B2E-49C63FC0AA48",
"token" : "0x60054cc",
"native_offset" : "0x0",
"filename" : "mscorlib.dll",
"sizeofimage" : "0x470000",
"timestamp" : "0xaf0ada7a",
"il_offset" : "0x00000"
}
,
{
"is_managed" : "true",
"guid" : "F3F41A8C-7505-4641-B318-00193DBBE389",
"token" : "0x6008e1b",
"native_offset" : "0x0",
"filename" : "UnityEditor.CoreModule.dll",
"sizeofimage" : "0x814000",
"timestamp" : "0x98e4bedd",
"il_offset" : "0x00000"
}
,
{
"is_managed" : "true",
"guid" : "E38A6D3E-E47C-43EB-9B2E-49C63FC0AA48",
"token" : "0x6001f7d",
"native_offset" : "0x0",
"filename" : "mscorlib.dll",
"sizeofimage" : "0x470000",
"timestamp" : "0xaf0ada7a",
"il_offset" : "0x00000"
}
,
{
"is_managed" : "true",
"guid" : "E38A6D3E-E47C-43EB-9B2E-49C63FC0AA48",
"token" : "0x6001f25",
"native_offset" : "0x0",
"filename" : "mscorlib.dll",
"sizeofimage" : "0x470000",
"timestamp" : "0xaf0ada7a",
"il_offset" : "0x00000"
}
,
{
"is_managed" : "true",
"guid" : "E38A6D3E-E47C-43EB-9B2E-49C63FC0AA48",
"token" : "0x6001f23",
"native_offset" : "0x0",
"filename" : "mscorlib.dll",
"sizeofimage" : "0x470000",
"timestamp" : "0xaf0ada7a",
"il_offset" : "0x00000"
}
,
{
"is_managed" : "true",
"guid" : "E38A6D3E-E47C-43EB-9B2E-49C63FC0AA48",
"token" : "0x6001f22",
"native_offset" : "0x0",
"filename" : "mscorlib.dll",
"sizeofimage" : "0x470000",
"timestamp" : "0xaf0ada7a",
"il_offset" : "0x00000"
}
,
{
"is_managed" : "true",
"guid" : "E38A6D3E-E47C-43EB-9B2E-49C63FC0AA48",
"token" : "0x6001f7f",
"native_offset" : "0x0",
"filename" : "mscorlib.dll",
"sizeofimage" : "0x470000",
"timestamp" : "0xaf0ada7a",
"il_offset" : "0x00000"
}
,
{
"is_managed" : "true",
"guid" : "E38A6D3E-E47C-43EB-9B2E-49C63FC0AA48",
"token" : "0x00000",
"native_offset" : "0x0",
"filename" : "mscorlib.dll",
"sizeofimage" : "0x470000",
"timestamp" : "0xaf0ada7a",
"il_offset" : "0x00000"
}
,
{
"is_managed" : "false",
"native_address" : "0x29a919b74",
"native_offset" : "0x00000"
}
,
{
"is_managed" : "false",
"native_address" : "0x29aa9f7ec",
"native_offset" : "0x00000"
}
,
{
"is_managed" : "false",
"native_address" : "0x29aaa13e8",
"native_offset" : "0x00000"
}
,
{
"is_managed" : "false",
"native_address" : "0x29aac172c",
"native_offset" : "0x00000"
}
,
{
"is_managed" : "false",
"native_address" : "0x29aac14e4",
"native_offset" : "0x00000"
}
,
{
"is_managed" : "false",
"native_address" : "0x29ab40d30",
"native_offset" : "0x00000"
}
,
{
"is_managed" : "false",
"native_address" : "0x29ab40cb8",
"native_offset" : "0x00000"
}
,
{
"is_managed" : "false",
"native_address" : "0x1afe1226c",
"native_offset" : "0x00000"
}
,
{
"is_managed" : "false",
"native_address" : "0x1afe0d08c",
"native_offset" : "0x00000"
}

]
},
{
"is_managed" : false,
"offset_free_hash" : "0x0",
"offset_rich_hash" : "0x0",
"crashed" : false,
"native_thread_id" : "0x29b1f3000",
"thread_info_addr" : "0x1278cf000",
"thread_name" : "Finalizer",
"ctx" : {
"IP" : "0x1afdd490c",
"SP" : "0x29b1f2dd0",
"BP" : "0x29b1f2e50"
},
"unmanaged_frames" : [
{
"is_managed" : "false",
"native_address" : "0x29a989ec0",
"native_offset" : "0x00000"
}
,
{
"is_managed" : "false",
"native_address" : "0x29aac08cc",
"native_offset" : "0x00000"
}
,
{
"is_managed" : "false",
"native_address" : "0x29aac0c28",
"native_offset" : "0x00000"
}
,
{
"is_managed" : "false",
"native_address" : "0x29aac09f0",
"native_offset" : "0x00000"
}
,
{
"is_managed" : "false",
"native_address" : "0x29a9cadc8",
"native_offset" : "0x00000"
}
,
{
"is_managed" : "false",
"native_address" : "0x1afe294c4",
"native_offset" : "0x00000"
}
,
{
"is_managed" : "false",
"native_address" : "0x29aafa3b4",
"native_offset" : "0x00000"
}
,
{
"is_managed" : "false",
"native_address" : "0x29aac1638",
"native_offset" : "0x00000"
}
,
{
"is_managed" : "false",
"native_address" : "0x29aac14e4",
"native_offset" : "0x00000"
}
,
{
"is_managed" : "false",
"native_address" : "0x29ab40d30",
"native_offset" : "0x00000"
}
,
{
"is_managed" : "false",
"native_address" : "0x29ab40cb8",
"native_offset" : "0x00000"
}
,
{
"is_managed" : "false",
"native_address" : "0x1afe1226c",
"native_offset" : "0x00000"
}
,
{
"is_managed" : "false",
"native_address" : "0x1afe0d08c",
"native_offset" : "0x00000"
}

]
}
]
}